{
  "label": "CRM Essentials by Keboola",
  "category_label": "Models",
  "branding": {
    "image_uri": "https://www.keboola.com/data/poweredByKeboola.png",
    "tagline": "Your CRM system is often the first data source to include in analytics. Using this Block not only provides fast time to value to get your first reports out to your sales leaders and executives, but also creates a foundation to build and expand reporting."
  },

  "constants": {
    "CONNECTION": {
      "label": "Connection Name",
      "value_constraint": "connection"
    },
    "SCHEMA_NAME": {
      "label": "Schema Name"
    },
    "CONFIG_PROJECT_NAME": {
      "label": "Config Project Name"
    },
    "SFDC_domain": {
      "label": "Salesforce domain URL",
      "description": "If you are using Salesforce, enter the base part of the URL in single quotes, such as 'keboola.lightning.force.com' - keep empty otherwise"
    },
    "hubspot_account_id": {
      "label": "Hubspot Account ID",
      "description": "If you are using Hubspot, enter your account ID in single quotes, such as '505715' - keep empty otherwise"
    },
      "pipedrive_domain": {
      "label": "Pipedrive Domain",
      "description": "If you are using Pipedrive, enter your domain in single quotes, such as 'keboola.pipedrive.com' - keep empty otherwise"
    }
  },
  "models": [
    {
      "name": "block_keboola_crm_essentials",
      "connection_constant": "CONNECTION"
    }
  ],
  "auxiliary_projects": [
    {
      "git_uri": "",
      "git_ref": "",
      "label": "CRM Essentials by Keboola Config",
      "constant_name": "CONFIG_PROJECT_NAME"
    }
  ]
}
